metadatamapping/__init__.py
metadatamapping/archs4.py
metadatamapping/concurrency.py
metadatamapping/dbutils.py
metadatamapping/exceptions.py
metadatamapping/geo.py
metadatamapping/link.py
metadatamapping/metadata.py
metadatamapping/metadatautils.py
metadatamapping/metasra.py
metadatamapping/obo.py
metadatamapping/parsers.py
metadatamapping/sparse.py
metadatamapping/summary.py
metadatamapping-1.2.2.dist-info/LICENSE
metadatamapping-1.2.2.dist-info/METADATA
metadatamapping-1.2.2.dist-info/WHEEL
metadatamapping-1.2.2.dist-info/top_level.txt
metadatamapping-1.2.2.dist-info/RECORD
