Metadata-Version: 2.1
Name: metadatamapping
Version: 1.2.2
Summary: A python library to fetch metadata from NCBI and MetaSRA for a list of NCBI accessions and data extraction from ARCHS4
Author-email: Daniel Malzl <daniel@menchelab.com>
License: MIT License
Project-URL: Homepage, https://github.com/dmalzl/metadatamapping
Keywords: database,metadata,biopython,bioinformatics
Classifier: License :: OSI Approved :: MIT License
Classifier: Programming Language :: Python
Classifier: Programming Language :: Python :: 3
Requires-Python: >=3.10
License-File: LICENSE
Requires-Dist: biopython >=1.81
Requires-Dist: h5py >=3.10.0
Requires-Dist: pandas >=2.1.3
Requires-Dist: anndata >=0.10.3
Requires-Dist: unidecode >=1.3.7
Requires-Dist: obonet >=1.0.0
Requires-Dist: regex >=2.5.135
